{
  "@input":"input",
  "@output":"udgang",
  "@if":"hvis",
  "@else":"andet",
  "@then":"derefter",
  "@or":"eller",
  "@and":"og",
  "@not":"ikke",
  "@false":"falsk",
  "@true":"sandt",
  "@do":"gøre",
  "@while":"mens",
  "@repeat":"gentag",
  "@times":"gange",
  "@break":"bryde",
  "@continue":"fortsæt",
  "@function":"funktion",
  "@random":"tilfældig",
  "@pow":"magt",
  "@sqr":"pladsen",
  "@sqrt":"square_root",
  "@round":"runde",
  "@floor":"etage",
  "@ceil":"ceil",
  "@abs":"absolute_value",
  "@sin":"sin",
  "@cos":"cos",
  "@tan":"tan",
  "@ctg":"ctg",
  "@arcsin":"arcsin",
  "@arccos":"arccos",
  "@arctan":"arctan",
  "@arcctg":"arcctg",
  "@log":"log",
  "@ln":"ln",
  "@lg":"lg",
  "@pi":"pi",
  "@e":"e"
}